searchsort/__init__.py
searchsort/searching.py
searchsort/sorting.py
searchsort-0.1.6.dist-info/LICENSE
searchsort-0.1.6.dist-info/METADATA
searchsort-0.1.6.dist-info/WHEEL
searchsort-0.1.6.dist-info/top_level.txt
searchsort-0.1.6.dist-info/RECORD
