Metadata-Version: 2.1
Name: searchsort
Version: 0.1.6
Summary: Almost all Searching and Sorting Algorithms for Python 3.x
Home-page: UNKNOWN
Author: Programmin-in-Python (MK)
Author-email: <kalanithi6014@gmail.com>
License: UNKNOWN
Project-URL: GitHub, https://github.com/Programmin-in-Python/searchsort
Keywords: python3,sort,search,sorting,searching,sorting-algorithms,searching-algorithms,search-sort,searchsort
Platform: UNKNOWN
Classifier: Development Status :: 5 - Production/Stable
Classifier: Intended Audience :: Developers
Classifier: License :: OSI Approved :: MIT License
Classifier: Natural Language :: English
Classifier: Operating System :: Unix
Classifier: Operating System :: MacOS :: MacOS X
Classifier: Operating System :: Microsoft :: Windows
Classifier: Operating System :: OS Independent
Classifier: Programming Language :: Python :: 3
Classifier: Programming Language :: Python :: 3 :: Only
Classifier: Topic :: Education
Classifier: Topic :: Software Development :: Libraries :: Python Modules
Requires-Python: >=3
